murky/__init__.py
murky/create_release_notes.py
murky/env_example1.yml
murky/env_example2.yml
murky/murky_create.sh
murky/murky_tool.py
murky/update_copyright_date.py
murky/tests/__init__.py
murky/tests/test_crn.py
murky/tests/test_ucd.py
murky-0.0.5.data/scripts/murky_create.sh
murky-0.0.5.dist-info/LICENSE
murky-0.0.5.dist-info/METADATA
murky-0.0.5.dist-info/WHEEL
murky-0.0.5.dist-info/entry_points.txt
murky-0.0.5.dist-info/top_level.txt
murky-0.0.5.dist-info/RECORD
