Metadata-Version: 2.1
Name: murky
Version: 0.0.5
Summary: The murky package provides tools for working with conda packages.
Author-email: "Pete R. Jemian" <prjemian+murky@gmail.com>
Maintainer-email: "Pete R. Jemian" <prjemian+murky@gmail.com>
License: Creative Commons Legal Code
Project-URL: Homepage, https://prjemian.github.io/murky/
Project-URL: Bug Tracker, https://github.com/prjemian/murky/issues
Keywords: python,conda,development,utilities
Classifier: Development Status :: 5 - Production/Stable
Classifier: Environment :: Console
Classifier: Intended Audience :: Science/Research
Classifier: License :: Freely Distributable
Classifier: License :: Public Domain
Classifier: Programming Language :: Python :: 3.12
Classifier: Programming Language :: Python :: 3.11
Classifier: Programming Language :: Python :: 3.10
Classifier: Programming Language :: Python :: 3.9
Classifier: Programming Language :: Python :: 3.8
Classifier: Programming Language :: Python
Classifier: Topic :: Software Development :: Libraries :: Python Modules
Classifier: Topic :: Software Development
Classifier: Topic :: Utilities
Requires-Python: >=3.8
License-File: LICENSE
